lyd/__init__.py
lyd/lyd_system_client.cp310-win_amd64.pyd
lyd/lyd_system_client.cp311-win_amd64.pyd
lyd/lyd_system_client.cp39-win_amd64.pyd
lyd/lyd_system_client.cpython-310-x86_64-linux-gnu.so
lyd/lyd_system_client.cpython-311-x86_64-linux-gnu.so
lyd/lyd_system_client.cpython-39-x86_64-linux-gnu.so
lyd/lyd_user_client.cp310-win_amd64.pyd
lyd/lyd_user_client.cp311-win_amd64.pyd
lyd/lyd_user_client.cp39-win_amd64.pyd
lyd/lyd_user_client.cpython-310-x86_64-linux-gnu.so
lyd/lyd_user_client.cpython-311-x86_64-linux-gnu.so
lyd/lyd_user_client.cpython-39-x86_64-linux-gnu.so
lyd-3.8.8.dist-info/METADATA
lyd-3.8.8.dist-info/WHEEL
lyd-3.8.8.dist-info/top_level.txt
lyd-3.8.8.dist-info/RECORD
