Metadata-Version: 2.1
Name: lyd
Version: 3.8.8
Summary: UNKNOWN
Home-page: https://lyg.ai
Author: LYG.AI
Author-email: team@lyg.ai
License: UNKNOWN
Platform: UNKNOWN
Classifier: Programming Language :: Python :: 3.9
Classifier: Programming Language :: Python :: 3.10
Classifier: Programming Language :: Python :: 3.11
Classifier: Operating System :: POSIX :: Linux
Classifier: Operating System :: Microsoft :: Windows
Requires-Dist: lyg
Requires-Dist: tqdm
